Workbook

Sheet Dashboard
B2: CARDLEDGER | COLLECTION CRM
B3: Inventory, customers, sales, and profit in one workbook.
B6: Pieces in stock | C6: =SUM(Inventory!L2:L501)
B7: Inventory purchase-cost value | C7: =SUM(Inventory!M2:M501)
B8: Estimated inventory market value | C8: =SUM(Inventory!N2:N501)
B9: Sales revenue | C9: =SUM(Sales!G2:G501)
B10: Realized profit | C10: =SUM(Sales!L2:L501)
B11: Pieces sold | C11: =SUM(Sales!E2:E501)
B12: Clients | C12: =COUNTA(Clients!A2:A501)
B13: Inventory / sales check flags | C13: =COUNTIF(Inventory!P2:P501,"?*")-COUNTIF(Inventory!P2:P501,"OK")+COUNTIF(Sales!Q2:Q501,"?*")-COUNTIF(Sales!Q2:Q501,"OK")+COUNTIF(Clients!H2:H501,"?*")-COUNTIF(Clients!H2:H501,"OK")
B16: Profit = revenue − card cost − fees − shipping. Excludes taxes and overhead.
B18: Blue cells contain formulas. Enter data in the white cells on each tab.

Sheet Inventory
A1: Lot ID | B1: Player / Card | C1: Sport | D1: Year | E1: Brand / Set | F1: Card # | G1: Grade | H1: Pieces purchased | I1: Purchase cost / card | J1: Est. value / card | K1: Pieces sold | L1: Pieces in stock | M1: Inventory cost value | N1: Est. inventory value | O1: Notes | P1: Check
K2: =IF(A2="","",SUMIF(Sales!$C$2:$C$501,A2,Sales!$E$2:$E$501)) | L2: =IF(A2="","",H2-K2) | M2: =IF(A2="","",ROUND(L2*I2,2)) | N2: =IF(A2="","",ROUND(L2*J2,2)) | P2: =IF(A2="","",IF(COUNTIF($A$2:$A$501,A2)>1,"Duplicate lot ID",IF(OR(B2="",H2="",I2="",J2=""),"Complete required fields",IF(L2<0,"OVER SOLD","OK"))))
K3: =IF(A3="","",SUMIF(Sales!$C$2:$C$501,A3,Sales!$E$2:$E$501)) | L3: =IF(A3="","",H3-K3) | M3: =IF(A3="","",ROUND(L3*I3,2)) | N3: =IF(A3="","",ROUND(L3*J3,2)) | P3: =IF(A3="","",IF(COUNTIF($A$2:$A$501,A3)>1,"Duplicate lot ID",IF(OR(B3="",H3="",I3="",J3=""),"Complete required fields",IF(L3<0,"OVER SOLD","OK"))))
K4: =IF(A4="","",SUMIF(Sales!$C$2:$C$501,A4,Sales!$E$2:$E$501)) | L4: =IF(A4="","",H4-K4) | M4: =IF(A4="","",ROUND(L4*I4,2)) | N4: =IF(A4="","",ROUND(L4*J4,2)) | P4: =IF(A4="","",IF(COUNTIF($A$2:$A$501,A4)>1,"Duplicate lot ID",IF(OR(B4="",H4="",I4="",J4=""),"Complete required fields",IF(L4<0,"OVER SOLD","OK"))))
K5: =IF(A5="","",SUMIF(Sales!$C$2:$C$501,A5,Sales!$E$2:$E$501)) | L5: =IF(A5="","",H5-K5) | M5: =IF(A5="","",ROUND(L5*I5,2)) | N5: =IF(A5="","",ROUND(L5*J5,2)) | P5: =IF(A5="","",IF(COUNTIF($A$2:$A$501,A5)>1,"Duplicate lot ID",IF(OR(B5="",H5="",I5="",J5=""),"Complete required fields",IF(L5<0,"OVER SOLD","OK"))))
K6: =IF(A6="","",SUMIF(Sales!$C$2:$C$501,A6,Sales!$E$2:$E$501)) | L6: =IF(A6="","",H6-K6) | M6: =IF(A6="","",ROUND(L6*I6,2)) | N6: =IF(A6="","",ROUND(L6*J6,2)) | P6: =IF(A6="","",IF(COUNTIF($A$2:$A$501,A6)>1,"Duplicate lot ID",IF(OR(B6="",H6="",I6="",J6=""),"Complete required fields",IF(L6<0,"OVER SOLD","OK"))))
K7: =IF(A7="","",SUMIF(Sales!$C$2:$C$501,A7,Sales!$E$2:$E$501)) | L7: =IF(A7="","",H7-K7) | M7: =IF(A7="","",ROUND(L7*I7,2)) | N7: =IF(A7="","",ROUND(L7*J7,2)) | P7: =IF(A7="","",IF(COUNTIF($A$2:$A$501,A7)>1,"Duplicate lot ID",IF(OR(B7="",H7="",I7="",J7=""),"Complete required fields",IF(L7<0,"OVER SOLD","OK"))))
K8: =IF(A8="","",SUMIF(Sales!$C$2:$C$501,A8,Sales!$E$2:$E$501)) | L8: =IF(A8="","",H8-K8) | M8: =IF(A8="","",ROUND(L8*I8,2)) | N8: =IF(A8="","",ROUND(L8*J8,2)) | P8: =IF(A8="","",IF(COUNTIF($A$2:$A$501,A8)>1,"Duplicate lot ID",IF(OR(B8="",H8="",I8="",J8=""),"Complete required fields",IF(L8<0,"OVER SOLD","OK"))))
K9: =IF(A9="","",SUMIF(Sales!$C$2:$C$501,A9,Sales!$E$2:$E$501)) | L9: =IF(A9="","",H9-K9) | M9: =IF(A9="","",ROUND(L9*I9,2)) | N9: =IF(A9="","",ROUND(L9*J9,2)) | P9: =IF(A9="","",IF(COUNTIF($A$2:$A$501,A9)>1,"Duplicate lot ID",IF(OR(B9="",H9="",I9="",J9=""),"Complete required fields",IF(L9<0,"OVER SOLD","OK"))))
K10: =IF(A10="","",SUMIF(Sales!$C$2:$C$501,A10,Sales!$E$2:$E$501)) | L10: =IF(A10="","",H10-K10) | M10: =IF(A10="","",ROUND(L10*I10,2)) | N10: =IF(A10="","",ROUND(L10*J10,2)) | P10: =IF(A10="","",IF(COUNTIF($A$2:$A$501,A10)>1,"Duplicate lot ID",IF(OR(B10="",H10="",I10="",J10=""),"Complete required fields",IF(L10<0,"OVER SOLD","OK"))))
K11: =IF(A11="","",SUMIF(Sales!$C$2:$C$501,A11,Sales!$E$2:$E$501)) | L11: =IF(A11="","",H11-K11) | M11: =IF(A11="","",ROUND(L11*I11,2)) | N11: =IF(A11="","",ROUND(L11*J11,2)) | P11: =IF(A11="","",IF(COUNTIF($A$2:$A$501,A11)>1,"Duplicate lot ID",IF(OR(B11="",H11="",I11="",J11=""),"Complete required fields",IF(L11<0,"OVER SOLD","OK"))))
K12: =IF(A12="","",SUMIF(Sales!$C$2:$C$501,A12,Sales!$E$2:$E$501)) | L12: =IF(A12="","",H12-K12) | M12: =IF(A12="","",ROUND(L12*I12,2)) | N12: =IF(A12="","",ROUND(L12*J12,2)) | P12: =IF(A12="","",IF(COUNTIF($A$2:$A$501,A12)>1,"Duplicate lot ID",IF(OR(B12="",H12="",I12="",J12=""),"Complete required fields",IF(L12<0,"OVER SOLD","OK"))))
K13: =IF(A13="","",SUMIF(Sales!$C$2:$C$501,A13,Sales!$E$2:$E$501)) | L13: =IF(A13="","",H13-K13) | M13: =IF(A13="","",ROUND(L13*I13,2)) | N13: =IF(A13="","",ROUND(L13*J13,2)) | P13: =IF(A13="","",IF(COUNTIF($A$2:$A$501,A13)>1,"Duplicate lot ID",IF(OR(B13="",H13="",I13="",J13=""),"Complete required fields",IF(L13<0,"OVER SOLD","OK"))))
... K501: =IF(A501="","",SUMIF(Sales!$C$2:$C$501,A501,Sales!$E$2:$E$501)) | L501: =IF(A501="","",H501-K501) | M501: =IF(A501="","",ROUND(L501*I501,2)) | N501: =IF(A501="","",ROUND(L501*J501,2)) | P501: =IF(A501="","",IF(COUNTIF($A$2:$A$501,A501)>1,"Duplicate lot ID",IF(OR(B501="",H501="",I501="",J501=""),"Complete required fields",IF(L501<0,"OVER SOLD","OK"))))

Sheet Sales
A1: Sale date | B1: Sale ID | C1: Lot ID | D1: Client ID (optional) | E1: Quantity sold | F1: Sale price / card | G1: Revenue | H1: Cost / card | I1: Cost basis | J1: Total fees | K1: Total shipping | L1: Profit | M1: Channel | N1: Notes | O1: Player / Card | P1: Client name | Q1: Check
G2: =IF(C2="","",ROUND(E2*F2,2)) | H2: =IF(C2="","",IFERROR(VLOOKUP(C2,Inventory!$A$2:$J$501,9,FALSE),0)) | I2: =IF(C2="","",ROUND(E2*H2,2)) | L2: =IF(C2="","",ROUND(G2-I2-J2-K2,2)) | O2: =IF(C2="","",IFERROR(VLOOKUP(C2,Inventory!$A$2:$B$501,2,FALSE),"Unknown lot")) | P2: =IF(D2="","",IFERROR(VLOOKUP(D2,Clients!$A$2:$B$501,2,FALSE),"Unknown client")) | Q2: =IF(C2="","",IF(COUNTIF(Inventory!$A$2:$A$501,C2)<>1,"Check lot ID",IF(OR(A2="",B2="",E2="",F2=""),"Complete required fields",IF(COUNTIF($B$2:$B$501,B2)>1,"Duplicate sale ID",IF(AND(D2<>"",COUNTIF(Clients!$A$2:$A$501,D2)<>1),"Check client ID",IF(VLOOKUP(C2,Inventory!$A$2:$L$501,12,FALSE)<0,"OVER SOLD","OK"))))))
G3: =IF(C3="","",ROUND(E3*F3,2)) | H3: =IF(C3="","",IFERROR(VLOOKUP(C3,Inventory!$A$2:$J$501,9,FALSE),0)) | I3: =IF(C3="","",ROUND(E3*H3,2)) | L3: =IF(C3="","",ROUND(G3-I3-J3-K3,2)) | O3: =IF(C3="","",IFERROR(VLOOKUP(C3,Inventory!$A$2:$B$501,2,FALSE),"Unknown lot")) | P3: =IF(D3="","",IFERROR(VLOOKUP(D3,Clients!$A$2:$B$501,2,FALSE),"Unknown client")) | Q3: =IF(C3="","",IF(COUNTIF(Inventory!$A$2:$A$501,C3)<>1,"Check lot ID",IF(OR(A3="",B3="",E3="",F3=""),"Complete required fields",IF(COUNTIF($B$2:$B$501,B3)>1,"Duplicate sale ID",IF(AND(D3<>"",COUNTIF(Clients!$A$2:$A$501,D3)<>1),"Check client ID",IF(VLOOKUP(C3,Inventory!$A$2:$L$501,12,FALSE)<0,"OVER SOLD","OK"))))))
G4: =IF(C4="","",ROUND(E4*F4,2)) | H4: =IF(C4="","",IFERROR(VLOOKUP(C4,Inventory!$A$2:$J$501,9,FALSE),0)) | I4: =IF(C4="","",ROUND(E4*H4,2)) | L4: =IF(C4="","",ROUND(G4-I4-J4-K4,2)) | O4: =IF(C4="","",IFERROR(VLOOKUP(C4,Inventory!$A$2:$B$501,2,FALSE),"Unknown lot")) | P4: =IF(D4="","",IFERROR(VLOOKUP(D4,Clients!$A$2:$B$501,2,FALSE),"Unknown client")) | Q4: =IF(C4="","",IF(COUNTIF(Inventory!$A$2:$A$501,C4)<>1,"Check lot ID",IF(OR(A4="",B4="",E4="",F4=""),"Complete required fields",IF(COUNTIF($B$2:$B$501,B4)>1,"Duplicate sale ID",IF(AND(D4<>"",COUNTIF(Clients!$A$2:$A$501,D4)<>1),"Check client ID",IF(VLOOKUP(C4,Inventory!$A$2:$L$501,12,FALSE)<0,"OVER SOLD","OK"))))))
G5: =IF(C5="","",ROUND(E5*F5,2)) | H5: =IF(C5="","",IFERROR(VLOOKUP(C5,Inventory!$A$2:$J$501,9,FALSE),0)) | I5: =IF(C5="","",ROUND(E5*H5,2)) | L5: =IF(C5="","",ROUND(G5-I5-J5-K5,2)) | O5: =IF(C5="","",IFERROR(VLOOKUP(C5,Inventory!$A$2:$B$501,2,FALSE),"Unknown lot")) | P5: =IF(D5="","",IFERROR(VLOOKUP(D5,Clients!$A$2:$B$501,2,FALSE),"Unknown client")) | Q5: =IF(C5="","",IF(COUNTIF(Inventory!$A$2:$A$501,C5)<>1,"Check lot ID",IF(OR(A5="",B5="",E5="",F5=""),"Complete required fields",IF(COUNTIF($B$2:$B$501,B5)>1,"Duplicate sale ID",IF(AND(D5<>"",COUNTIF(Clients!$A$2:$A$501,D5)<>1),"Check client ID",IF(VLOOKUP(C5,Inventory!$A$2:$L$501,12,FALSE)<0,"OVER SOLD","OK"))))))
G6: =IF(C6="","",ROUND(E6*F6,2)) | H6: =IF(C6="","",IFERROR(VLOOKUP(C6,Inventory!$A$2:$J$501,9,FALSE),0)) | I6: =IF(C6="","",ROUND(E6*H6,2)) | L6: =IF(C6="","",ROUND(G6-I6-J6-K6,2)) | O6: =IF(C6="","",IFERROR(VLOOKUP(C6,Inventory!$A$2:$B$501,2,FALSE),"Unknown lot")) | P6: =IF(D6="","",IFERROR(VLOOKUP(D6,Clients!$A$2:$B$501,2,FALSE),"Unknown client")) | Q6: =IF(C6="","",IF(COUNTIF(Inventory!$A$2:$A$501,C6)<>1,"Check lot ID",IF(OR(A6="",B6="",E6="",F6=""),"Complete required fields",IF(COUNTIF($B$2:$B$501,B6)>1,"Duplicate sale ID",IF(AND(D6<>"",COUNTIF(Clients!$A$2:$A$501,D6)<>1),"Check client ID",IF(VLOOKUP(C6,Inventory!$A$2:$L$501,12,FALSE)<0,"OVER SOLD","OK"))))))
G7: =IF(C7="","",ROUND(E7*F7,2)) | H7: =IF(C7="","",IFERROR(VLOOKUP(C7,Inventory!$A$2:$J$501,9,FALSE),0)) | I7: =IF(C7="","",ROUND(E7*H7,2)) | L7: =IF(C7="","",ROUND(G7-I7-J7-K7,2)) | O7: =IF(C7="","",IFERROR(VLOOKUP(C7,Inventory!$A$2:$B$501,2,FALSE),"Unknown lot")) | P7: =IF(D7="","",IFERROR(VLOOKUP(D7,Clients!$A$2:$B$501,2,FALSE),"Unknown client")) | Q7: =IF(C7="","",IF(COUNTIF(Inventory!$A$2:$A$501,C7)<>1,"Check lot ID",IF(OR(A7="",B7="",E7="",F7=""),"Complete required fields",IF(COUNTIF($B$2:$B$501,B7)>1,"Duplicate sale ID",IF(AND(D7<>"",COUNTIF(Clients!$A$2:$A$501,D7)<>1),"Check client ID",IF(VLOOKUP(C7,Inventory!$A$2:$L$501,12,FALSE)<0,"OVER SOLD","OK"))))))
G8: =IF(C8="","",ROUND(E8*F8,2)) | H8: =IF(C8="","",IFERROR(VLOOKUP(C8,Inventory!$A$2:$J$501,9,FALSE),0)) | I8: =IF(C8="","",ROUND(E8*H8,2)) | L8: =IF(C8="","",ROUND(G8-I8-J8-K8,2)) | O8: =IF(C8="","",IFERROR(VLOOKUP(C8,Inventory!$A$2:$B$501,2,FALSE),"Unknown lot")) | P8: =IF(D8="","",IFERROR(VLOOKUP(D8,Clients!$A$2:$B$501,2,FALSE),"Unknown client")) | Q8: =IF(C8="","",IF(COUNTIF(Inventory!$A$2:$A$501,C8)<>1,"Check lot ID",IF(OR(A8="",B8="",E8="",F8=""),"Complete required fields",IF(COUNTIF($B$2:$B$501,B8)>1,"Duplicate sale ID",IF(AND(D8<>"",COUNTIF(Clients!$A$2:$A$501,D8)<>1),"Check client ID",IF(VLOOKUP(C8,Inventory!$A$2:$L$501,12,FALSE)<0,"OVER SOLD","OK"))))))
G9: =IF(C9="","",ROUND(E9*F9,2)) | H9: =IF(C9="","",IFERROR(VLOOKUP(C9,Inventory!$A$2:$J$501,9,FALSE),0)) | I9: =IF(C9="","",ROUND(E9*H9,2)) | L9: =IF(C9="","",ROUND(G9-I9-J9-K9,2)) | O9: =IF(C9="","",IFERROR(VLOOKUP(C9,Inventory!$A$2:$B$501,2,FALSE),"Unknown lot")) | P9: =IF(D9="","",IFERROR(VLOOKUP(D9,Clients!$A$2:$B$501,2,FALSE),"Unknown client")) | Q9: =IF(C9="","",IF(COUNTIF(Inventory!$A$2:$A$501,C9)<>1,"Check lot ID",IF(OR(A9="",B9="",E9="",F9=""),"Complete required fields",IF(COUNTIF($B$2:$B$501,B9)>1,"Duplicate sale ID",IF(AND(D9<>"",COUNTIF(Clients!$A$2:$A$501,D9)<>1),"Check client ID",IF(VLOOKUP(C9,Inventory!$A$2:$L$501,12,FALSE)<0,"OVER SOLD","OK"))))))
G10: =IF(C10="","",ROUND(E10*F10,2)) | H10: =IF(C10="","",IFERROR(VLOOKUP(C10,Inventory!$A$2:$J$501,9,FALSE),0)) | I10: =IF(C10="","",ROUND(E10*H10,2)) | L10: =IF(C10="","",ROUND(G10-I10-J10-K10,2)) | O10: =IF(C10="","",IFERROR(VLOOKUP(C10,Inventory!$A$2:$B$501,2,FALSE),"Unknown lot")) | P10: =IF(D10="","",IFERROR(VLOOKUP(D10,Clients!$A$2:$B$501,2,FALSE),"Unknown client")) | Q10: =IF(C10="","",IF(COUNTIF(Inventory!$A$2:$A$501,C10)<>1,"Check lot ID",IF(OR(A10="",B10="",E10="",F10=""),"Complete required fields",IF(COUNTIF($B$2:$B$501,B10)>1,"Duplicate sale ID",IF(AND(D10<>"",COUNTIF(Clients!$A$2:$A$501,D10)<>1),"Check client ID",IF(VLOOKUP(C10,Inventory!$A$2:$L$501,12,FALSE)<0,"OVER SOLD","OK"))))))
G11: =IF(C11="","",ROUND(E11*F11,2)) | H11: =IF(C11="","",IFERROR(VLOOKUP(C11,Inventory!$A$2:$J$501,9,FALSE),0)) | I11: =IF(C11="","",ROUND(E11*H11,2)) | L11: =IF(C11="","",ROUND(G11-I11-J11-K11,2)) | O11: =IF(C11="","",IFERROR(VLOOKUP(C11,Inventory!$A$2:$B$501,2,FALSE),"Unknown lot")) | P11: =IF(D11="","",IFERROR(VLOOKUP(D11,Clients!$A$2:$B$501,2,FALSE),"Unknown client")) | Q11: =IF(C11="","",IF(COUNTIF(Inventory!$A$2:$A$501,C11)<>1,"Check lot ID",IF(OR(A11="",B11="",E11="",F11=""),"Complete required fields",IF(COUNTIF($B$2:$B$501,B11)>1,"Duplicate sale ID",IF(AND(D11<>"",COUNTIF(Clients!$A$2:$A$501,D11)<>1),"Check client ID",IF(VLOOKUP(C11,Inventory!$A$2:$L$501,12,FALSE)<0,"OVER SOLD","OK"))))))
G12: =IF(C12="","",ROUND(E12*F12,2)) | H12: =IF(C12="","",IFERROR(VLOOKUP(C12,Inventory!$A$2:$J$501,9,FALSE),0)) | I12: =IF(C12="","",ROUND(E12*H12,2)) | L12: =IF(C12="","",ROUND(G12-I12-J12-K12,2)) | O12: =IF(C12="","",IFERROR(VLOOKUP(C12,Inventory!$A$2:$B$501,2,FALSE),"Unknown lot")) | P12: =IF(D12="","",IFERROR(VLOOKUP(D12,Clients!$A$2:$B$501,2,FALSE),"Unknown client")) | Q12: =IF(C12="","",IF(COUNTIF(Inventory!$A$2:$A$501,C12)<>1,"Check lot ID",IF(OR(A12="",B12="",E12="",F12=""),"Complete required fields",IF(COUNTIF($B$2:$B$501,B12)>1,"Duplicate sale ID",IF(AND(D12<>"",COUNTIF(Clients!$A$2:$A$501,D12)<>1),"Check client ID",IF(VLOOKUP(C12,Inventory!$A$2:$L$501,12,FALSE)<0,"OVER SOLD","OK"))))))
G13: =IF(C13="","",ROUND(E13*F13,2)) | H13: =IF(C13="","",IFERROR(VLOOKUP(C13,Inventory!$A$2:$J$501,9,FALSE),0)) | I13: =IF(C13="","",ROUND(E13*H13,2)) | L13: =IF(C13="","",ROUND(G13-I13-J13-K13,2)) | O13: =IF(C13="","",IFERROR(VLOOKUP(C13,Inventory!$A$2:$B$501,2,FALSE),"Unknown lot")) | P13: =IF(D13="","",IFERROR(VLOOKUP(D13,Clients!$A$2:$B$501,2,FALSE),"Unknown client")) | Q13: =IF(C13="","",IF(COUNTIF(Inventory!$A$2:$A$501,C13)<>1,"Check lot ID",IF(OR(A13="",B13="",E13="",F13=""),"Complete required fields",IF(COUNTIF($B$2:$B$501,B13)>1,"Duplicate sale ID",IF(AND(D13<>"",COUNTIF(Clients!$A$2:$A$501,D13)<>1),"Check client ID",IF(VLOOKUP(C13,Inventory!$A$2:$L$501,12,FALSE)<0,"OVER SOLD","OK"))))))
... G501: =IF(C501="","",ROUND(E501*F501,2)) | H501: =IF(C501="","",IFERROR(VLOOKUP(C501,Inventory!$A$2:$J$501,9,FALSE),0)) | I501: =IF(C501="","",ROUND(E501*H501,2)) | L501: =IF(C501="","",ROUND(G501-I501-J501-K501,2)) | O501: =IF(C501="","",IFERROR(VLOOKUP(C501,Inventory!$A$2:$B$501,2,FALSE),"Unknown lot")) | P501: =IF(D501="","",IFERROR(VLOOKUP(D501,Clients!$A$2:$B$501,2,FALSE),"Unknown client")) | Q501: =IF(C501="","",IF(COUNTIF(Inventory!$A$2:$A$501,C501)<>1,"Check lot ID",IF(OR(A501="",B501="",E501="",F501=""),"Complete required fields",IF(COUNTIF($B$2:$B$501,B501)>1,"Duplicate sale ID",IF(AND(D501<>"",COUNTIF(Clients!$A$2:$A$501,D501)<>1),"Check client ID",IF(VLOOKUP(C501,Inventory!$A$2:$L$501,12,FALSE)<0,"OVER SOLD","OK"))))))

Sheet Clients
A1: Client ID | B1: Client name | C1: Email | D1: Phone | E1: Notes | F1: Sale count | G1: Total spending | H1: Check
F2: =IF(A2="","",COUNTIF(Sales!$D$2:$D$501,A2)) | G2: =IF(A2="","",SUMIF(Sales!$D$2:$D$501,A2,Sales!$G$2:$G$501)) | H2: =IF(A2="","",IF(COUNTIF($A$2:$A$501,A2)>1,"Duplicate client ID",IF(B2="","Add client name","OK")))
F3: =IF(A3="","",COUNTIF(Sales!$D$2:$D$501,A3)) | G3: =IF(A3="","",SUMIF(Sales!$D$2:$D$501,A3,Sales!$G$2:$G$501)) | H3: =IF(A3="","",IF(COUNTIF($A$2:$A$501,A3)>1,"Duplicate client ID",IF(B3="","Add client name","OK")))
F4: =IF(A4="","",COUNTIF(Sales!$D$2:$D$501,A4)) | G4: =IF(A4="","",SUMIF(Sales!$D$2:$D$501,A4,Sales!$G$2:$G$501)) | H4: =IF(A4="","",IF(COUNTIF($A$2:$A$501,A4)>1,"Duplicate client ID",IF(B4="","Add client name","OK")))
F5: =IF(A5="","",COUNTIF(Sales!$D$2:$D$501,A5)) | G5: =IF(A5="","",SUMIF(Sales!$D$2:$D$501,A5,Sales!$G$2:$G$501)) | H5: =IF(A5="","",IF(COUNTIF($A$2:$A$501,A5)>1,"Duplicate client ID",IF(B5="","Add client name","OK")))
F6: =IF(A6="","",COUNTIF(Sales!$D$2:$D$501,A6)) | G6: =IF(A6="","",SUMIF(Sales!$D$2:$D$501,A6,Sales!$G$2:$G$501)) | H6: =IF(A6="","",IF(COUNTIF($A$2:$A$501,A6)>1,"Duplicate client ID",IF(B6="","Add client name","OK")))
F7: =IF(A7="","",COUNTIF(Sales!$D$2:$D$501,A7)) | G7: =IF(A7="","",SUMIF(Sales!$D$2:$D$501,A7,Sales!$G$2:$G$501)) | H7: =IF(A7="","",IF(COUNTIF($A$2:$A$501,A7)>1,"Duplicate client ID",IF(B7="","Add client name","OK")))
F8: =IF(A8="","",COUNTIF(Sales!$D$2:$D$501,A8)) | G8: =IF(A8="","",SUMIF(Sales!$D$2:$D$501,A8,Sales!$G$2:$G$501)) | H8: =IF(A8="","",IF(COUNTIF($A$2:$A$501,A8)>1,"Duplicate client ID",IF(B8="","Add client name","OK")))
F9: =IF(A9="","",COUNTIF(Sales!$D$2:$D$501,A9)) | G9: =IF(A9="","",SUMIF(Sales!$D$2:$D$501,A9,Sales!$G$2:$G$501)) | H9: =IF(A9="","",IF(COUNTIF($A$2:$A$501,A9)>1,"Duplicate client ID",IF(B9="","Add client name","OK")))
F10: =IF(A10="","",COUNTIF(Sales!$D$2:$D$501,A10)) | G10: =IF(A10="","",SUMIF(Sales!$D$2:$D$501,A10,Sales!$G$2:$G$501)) | H10: =IF(A10="","",IF(COUNTIF($A$2:$A$501,A10)>1,"Duplicate client ID",IF(B10="","Add client name","OK")))
F11: =IF(A11="","",COUNTIF(Sales!$D$2:$D$501,A11)) | G11: =IF(A11="","",SUMIF(Sales!$D$2:$D$501,A11,Sales!$G$2:$G$501)) | H11: =IF(A11="","",IF(COUNTIF($A$2:$A$501,A11)>1,"Duplicate client ID",IF(B11="","Add client name","OK")))
F12: =IF(A12="","",COUNTIF(Sales!$D$2:$D$501,A12)) | G12: =IF(A12="","",SUMIF(Sales!$D$2:$D$501,A12,Sales!$G$2:$G$501)) | H12: =IF(A12="","",IF(COUNTIF($A$2:$A$501,A12)>1,"Duplicate client ID",IF(B12="","Add client name","OK")))
F13: =IF(A13="","",COUNTIF(Sales!$D$2:$D$501,A13)) | G13: =IF(A13="","",SUMIF(Sales!$D$2:$D$501,A13,Sales!$G$2:$G$501)) | H13: =IF(A13="","",IF(COUNTIF($A$2:$A$501,A13)>1,"Duplicate client ID",IF(B13="","Add client name","OK")))
... F501: =IF(A501="","",COUNTIF(Sales!$D$2:$D$501,A501)) | G501: =IF(A501="","",SUMIF(Sales!$D$2:$D$501,A501,Sales!$G$2:$G$501)) | H501: =IF(A501="","",IF(COUNTIF($A$2:$A$501,A501)>1,"Duplicate client ID",IF(B501="","Add client name","OK")))

Sheet Start Here
B2: CARDLEDGER — GOOGLE SHEETS QUICK START
B3: Upload this XLSX to Google Drive. Right-click → Open with → Google Sheets, then File → Save as Google Sheets.
B4: 1. Inventory: use one unique Lot ID per purchase batch (example LOT-001). Enter player, sport, pieces purchased, purchase cost per card, and estimated market value per card.
B5: 2. Restocking: add a NEW inventory row with a NEW Lot ID for each purchase batch. Do not increase old purchase quantities or change old purchase costs after recording sales.
B6: 3. Clients: assign unique Client IDs (example CLI-001), then enter names, email, phone, and notes.
B7: 4. Sales: enter date, unique Sale ID (SALE-001), Lot ID, optional Client ID, quantity, sale price per card, total fees, and total shipping. Formula columns calculate revenue, cost, profit, names, and checks.
B8: 5. A sale spanning multiple lots must use one Sales row per lot, each with a unique Sale ID. Divide fees and shipping across those rows; do not count them twice.
B9: 6. Dashboard updates automatically. Check flags must be resolved before relying on totals. Overselling is flagged, but spreadsheets do not prevent simultaneous users from selling the same stock.
B10: 7. Dollar amounts are USD. Purchase costs should include acquisition costs allocated per card. Inventory market estimates are manually entered, not live prices.
B11: 8. Client spending is gross sale revenue, not net profit. Inventory price estimates can be changed; historical purchase cost must stay fixed to preserve sales profit.
B12: 9. This template supports 500 input rows per tab. To expand it, copy formulas and validation downward AND extend all ranges in formulas and dropdowns.
B13: 10. Blue cells are formulas; do not type over them. After converting to Google Sheets, use Data → Protect sheets and ranges to protect formula columns.
... B17: 14. Google Sheets may change validation presentation during conversion. Verify dropdowns and formulas after import. This file was generated and structurally validated; Google Sheets import has not been tested in a connected account.
